muxi/__init__.py
muxi/auth.py
muxi/errors.py
muxi/formation.py
muxi/server.py
muxi/transport.py
muxi/version.py
muxi/client/__init__.py
muxi-0.20260107.253.dist-info/licenses/LICENSE
muxi-0.20260107.253.dist-info/METADATA
muxi-0.20260107.253.dist-info/WHEEL
muxi-0.20260107.253.dist-info/top_level.txt
muxi-0.20260107.253.dist-info/RECORD
