Metadata-Version: 2.4
Name: muxi
Version: 0.20260107.253
Summary: MUXI Python SDK
Home-page: https://muxi.org
Author: MUXI Team
Author-email: MUXI Team <dev@muxi.org>
License: Apache-2.0
Project-URL: Homepage, https://muxi.org
Project-URL: Source, https://github.com/muxi-ai/muxi-python
Project-URL: Issues, https://github.com/muxi-ai/muxi-python/issues
Classifier: Development Status :: 4 - Beta
Classifier: Intended Audience :: Developers
Classifier: Topic :: Software Development :: Libraries
Classifier: Programming Language :: Python
Classifier: Programming Language :: Python :: 3
Classifier: Programming Language :: Python :: 3.10
Classifier: Programming Language :: Python :: 3.11
Classifier: Programming Language :: Python :: 3.12
Classifier: License :: OSI Approved :: Apache Software License
Classifier: Operating System :: OS Independent
Requires-Python: >=3.10
License-File: LICENSE
Requires-Dist: httpx>=0.24.0
Dynamic: author
Dynamic: home-page
Dynamic: license-file
Dynamic: requires-python
